dynamic_forest/__init__.py
dynamic_forest/forest.py
dynamic_forest-1.0.1.dist-info/METADATA
dynamic_forest-1.0.1.dist-info/WHEEL
dynamic_forest-1.0.1.dist-info/licenses/LICENSE
dynamic_forest-1.0.1.dist-info/RECORD
