Metadata-Version: 2.4
Name: dynamic_forest
Version: 1.0.1
Summary: A dynamic forest data structure.
Project-URL: Homepage, https://github.com/pmacg/dynamic-forest
Project-URL: Issues, https://github.com/pmacg/dynamic-forest/issues
Author-email: Peter Macgregor <prm4@st-andrews.ac.uk>
License-File: LICENSE
Classifier: License :: OSI Approved :: MIT License
Classifier: Operating System :: OS Independent
Classifier: Programming Language :: Python :: 3
Requires-Python: >=3.8
